<?xml version="1.0"?>
<m> <p x="-0.623091821106" y="-0.255511043168" z="-0.73923655841"/>
 <p x="0.06003575091" y="0.459901711819" z="-0.885937991103"/>
 <p x="0.346268037586" y="-0.494162351134" z="-0.797434647396"/>
 <p x="-0.969359858692" y="0.238651307966" z="0.0581980889865"/>
 <p x="-0.286232286676" y="0.954064062952" z="-0.0885033437062"/>
 <p x="0.683127572016" y="0.715412754986" z="-0.146701432693"/>
 <p x="0.969359858692" y="-0.238651307966" z="-0.0581980889865"/>
 <p x="0.286232286676" y="-0.954064062952" z="0.0885033437062"/>
 <p x="-0.683127572016" y="-0.715412754986" z="0.146701432693"/>
 <p x="0.204561105984" y="0.653082833474" z="0.729134806837"/>
 <p x="-0.478566466033" y="-0.0623299215124" z="0.875836239529"/>
 <p x="0.49079339266" y="-0.300981229479" z="0.817638150543"/>
 <f><v>0</v><v>1</v><v>2</v></f>
 <f><v>1</v><v>0</v><v>3</v><v>4</v></f>
 <f><v>1</v><v>4</v><v>5</v></f>
 <f><v>2</v><v>1</v><v>5</v><v>6</v></f>
 <f><v>2</v><v>6</v><v>7</v></f>
 <f><v>0</v><v>2</v><v>7</v><v>8</v></f>
 <f><v>0</v><v>8</v><v>3</v></f>
 <f><v>9</v><v>10</v><v>11</v></f>
 <f><v>10</v><v>9</v><v>4</v><v>3</v></f>
 <f><v>10</v><v>3</v><v>8</v></f>
 <f><v>11</v><v>10</v><v>8</v><v>7</v></f>
 <f><v>11</v><v>7</v><v>6</v></f>
 <f><v>9</v><v>11</v><v>6</v><v>5</v></f>
 <f><v>9</v><v>5</v><v>4</v></f>
</m>
